setup.cfg
setup.py
dist_helloworldmod1/__init__.py
dist_helloworldmod1/helloworldmod1.py
dist_helloworldmod1.egg-info/PKG-INFO
dist_helloworldmod1.egg-info/SOURCES.txt
dist_helloworldmod1.egg-info/dependency_links.txt
dist_helloworldmod1.egg-info/top_level.txt