Metadata-Version: 1.0
Name: dist-helloworldmod1
Version: 0.0
Summary: Some discription
Home-page: UNKNOWN
Author: UNKNOWN
Author-email: kolyaleonof@yandex.ru
License: UNKNOWN
Platform: UNKNOWN
